siriuscommon/__init__.py
siriuscommon/archiver/__init__.py
siriuscommon/archiver/types.py
siriuscommon/devices/__init__.py
siriuscommon/devices/data_model/__init__.py
siriuscommon/devices/data_model/agilent.py
siriuscommon/devices/data_model/mks.py
siriuscommon/devices/spreadsheet/__init__.py
siriuscommon/devices/spreadsheet/parser.py
siriuscommon/taiga/__init__.py
siriuscommon/taiga/app.py
siriuscommon/taiga/client.py
siriuscommon/zabbix/__init__.py
siriuscommon/zabbix/types.py
siriuscommon-2.1.1.data/scripts/archiver-get-pv-status.py
siriuscommon-2.1.1.data/scripts/archiver-get-pvs-by-dropped-events-type-change.py
siriuscommon-2.1.1.data/scripts/archiver-get-pvs-disconnected.py
siriuscommon-2.1.1.data/scripts/archiver-get-pvs-matching.py
siriuscommon-2.1.1.data/scripts/archiver-get-pvs-paused.py
siriuscommon-2.1.1.data/scripts/zabbix-get-item-history.py
siriuscommon-2.1.1.data/scripts/zabbix-get-item-trend.py
siriuscommon-2.1.1.data/scripts/zabbix-get-items-from-host.py
siriuscommon-2.1.1.dist-info/METADATA
siriuscommon-2.1.1.dist-info/WHEEL
siriuscommon-2.1.1.dist-info/entry_points.txt
siriuscommon-2.1.1.dist-info/top_level.txt
siriuscommon-2.1.1.dist-info/zip-safe
siriuscommon-2.1.1.dist-info/RECORD
