Metadata-Version: 2.1
Name: siriuscommon
Version: 2.1.1
Summary: Commons for Sirius applications
Home-page: https://github.com/lnls-sirius/sirius-common/
Author: Carneiro, Claudio F.
License: GNU GPLv3
Download-URL: https://github.com/lnls-sirius/sirius-common
Platform: UNKNOWN
Classifier: Intended Audience :: Science/Research
Classifier: Operating System :: OS Independent
Classifier: Programming Language :: Python :: 3 :: Only
Classifier: Programming Language :: Python :: 3
Classifier: Programming Language :: Python :: 3.6
Classifier: Programming Language :: Python :: 3.7
Classifier: Programming Language :: Python :: 3.8
Classifier: Programming Language :: Python :: 3.9
Classifier: Programming Language :: Python
Classifier: Topic :: Scientific/Engineering
Requires-Python: >=3.6
Requires-Dist: pandas
Requires-Dist: python-taiga (==1.0.0)
Requires-Dist: pyzabbix (==1.0.0)
Requires-Dist: requests (>=2.22.0)
Requires-Dist: xlsxwriter (>=3.0.1)
